datastructs/__init__.py
datastructs/datastructs.py
datastructs_sparkles58-1.0.5.dist-info/METADATA
datastructs_sparkles58-1.0.5.dist-info/WHEEL
datastructs_sparkles58-1.0.5.dist-info/top_level.txt
datastructs_sparkles58-1.0.5.dist-info/RECORD
