Metadata-Version: 2.1
Name: datastructs-sparkles58
Version: 1.0.5
Summary: Queues and trees.
Home-page: https://github.com/sparklesunicorn/datastructs
Author: Ezra SB
Author-email: ezzysuger717@gmail.com
License: UNKNOWN
Platform: UNKNOWN
Classifier: Programming Language :: Python :: 3
Classifier: License :: OSI Approved :: MIT License
Classifier: Operating System :: OS Independent
Requires-Python: >=3.6
